demo/demo_server.py
jsonrpc_mcp/__init__.py
jsonrpc_mcp/fastmcp_server.py
jsonrpc_mcp/server.py
jsonrpc_mcp/utils.py
fetch_jsonpath_mcp-1.1.2.dist-info/METADATA
fetch_jsonpath_mcp-1.1.2.dist-info/WHEEL
fetch_jsonpath_mcp-1.1.2.dist-info/entry_points.txt
fetch_jsonpath_mcp-1.1.2.dist-info/RECORD
