Metadata-Version: 2.4
Name: fetch-jsonpath-mcp
Version: 1.1.2
Summary: An MCP server for fetching and extracting JSON data using JSONPath
Author-email: ackness <ackness8@gmail.com>
Requires-Python: >=3.10
Requires-Dist: beautifulsoup4>=4.13.4
Requires-Dist: fastapi>=0.116.1
Requires-Dist: httpx>=0.28.1
Requires-Dist: jsonpath-ng>=1.7.0
Requires-Dist: markdownify>=1.2.0
Requires-Dist: mcp[cli]>=1.12.4
Requires-Dist: uvicorn>=0.35.0
